tabtool
