Metadata-Version: 1.1
Name: tabtool
Version: 0.2.0
Summary: Utility to operate with tab separated files
Home-page: https://github.com/pavlov99/tabtool
Author: Kirill Pavlov
Author-email: kirill.pavlov@phystech.edu
License: MIT
Platform: UNKNOWN
Classifier: Development Status :: 3 - Alpha
Classifier: Environment :: Console
Classifier: License :: OSI Approved :: MIT License
Classifier: Natural Language :: English
Classifier: Operating System :: OS Independent
Classifier: Programming Language :: Python :: 2.7
Classifier: Programming Language :: Python :: 3.2
Classifier: Programming Language :: Python :: 3.3
Classifier: Topic :: Software Development :: Libraries :: Python Modules
